tensorgator/__init__.py
tensorgator/constants.py
tensorgator/coord_conv.py
tensorgator/coverage.py
tensorgator/prop_cpu.py
tensorgator/prop_cuda.py
tensorgator/propagation.py
tensorgator/setup.py
tensorgator/visibility.py
tensorgator/examples/3d_orbit_animation_google_colab.ipynb
tensorgator/examples/benchmark_google_colab.ipynb
tensorgator/examples/coverage_map.png
tensorgator/examples/coverage_map_google_colab.ipynb
tensorgator-0.1.1.dist-info/licenses/LICENSE
tensorgator-0.1.1.dist-info/METADATA
tensorgator-0.1.1.dist-info/WHEEL
tensorgator-0.1.1.dist-info/top_level.txt
tensorgator-0.1.1.dist-info/RECORD
