Metadata-Version: 2.4
Name: tensorgator
Version: 0.1.1
Summary: CUDA-accelerated Satellite Propagation
Home-page: https://github.com/ApoPeri/TensorGator
Author: ApoPeri
Author-email: ApoPeri <ApoPeri@protonmail.com>
License: MIT License
Requires-Python: >=3.7
License-File: LICENSE
Requires-Dist: numpy
Requires-Dist: matplotlib
Requires-Dist: numba
Dynamic: author
Dynamic: home-page
Dynamic: license-file
Dynamic: requires-python
